<?xml version="1.0" encoding="UTF-8" standalone="no" ?>
<tupleModel xmlns="http://www.ibm.com/xmlns/prod/streams/spl/tuple" class="BeJwrMSk2yUvMTS02LcksyUktNjRISS1ILCrJTc0rcTMrTsxJLKoEAPpZA3L" equalitySupported="true" facade="false" splType="tuple&lt;rstring name,rstring title,rstring department,float64 salary>" xmlns:xsi="http://www.w3.org/2001/XMLSchema-instance">

  <headers/>

  <attributes>
    <attribute>
      <name>name</name>
      <cppType>SPL::rstring</cppType>
      <splType>rstring</splType>
    </attribute>
    <attribute>
      <name>title</name>
      <cppType>SPL::rstring</cppType>
      <splType>rstring</splType>
    </attribute>
    <attribute>
      <name>department</name>
      <cppType>SPL::rstring</cppType>
      <splType>rstring</splType>
    </attribute>
    <attribute>
      <name>salary</name>
      <cppType>SPL::float64</cppType>
      <splType>float64</splType>
    </attribute>
  </attributes>

</tupleModel>
